processing_pypelines-0.0.96.dist-info/METADATA
processing_pypelines-0.0.96.dist-info/WHEEL
processing_pypelines-0.0.96.dist-info/entry_points.txt
processing_pypelines-0.0.96.dist-info/licenses/LICENSE
pypelines/__init__.py
pypelines/arguments.py
pypelines/celery_tasks.py
pypelines/disk.py
pypelines/examples.py
pypelines/extend_pandas/__init__.py
pypelines/extend_pandas/__init__.pyi
pypelines/extend_pandas/py.typed
pypelines/extend_pandas/typing.py
pypelines/graphs.py
pypelines/loggs.py
pypelines/multisession.py
pypelines/pickle_backend.py
pypelines/pipelines.py
pypelines/pipes.py
pypelines/sessions.py
pypelines/steps.py
pypelines/tasks.py
pypelines/utils.py
pypelines/versions.py
processing_pypelines-0.0.96.dist-info/RECORD
