Metadata-Version: 2.1
Name: processing-pypelines
Version: 0.0.96
Summary: Framework to organize processing code outputs to/from disk, processing chaining and versionning with a common easy to use api
Author-Email: =?utf-8?q?Timoth=C3=A9_Jost-Mousseau?= <timothe.jost-mousseau@pasteur.fr>
Maintainer-Email: =?utf-8?q?Timoth=C3=A9_Jost-Mousseau?= <timothe.jost-mousseau@pasteur.fr>
License: MIT
Project-URL: homepage, https://gitlab.pasteur.fr/haisslab/data-management/pypelines
Project-URL: repository, https://gitlab.pasteur.fr/haisslab/data-management/pypelines
Project-URL: documentation, https://gitlab.pasteur.fr/haisslab/data-management/pypelines
Requires-Python: >=3.10
Requires-Dist: coloredlogs>=15.0.1
Requires-Dist: dynaconf>=3.2.4
Requires-Dist: natsort>=8.4.0
Requires-Dist: networkx>=3.1
Requires-Dist: numpy
Requires-Dist: matplotlib
Requires-Dist: pandas>=2.1.4
Provides-Extra: celery
Requires-Dist: celery>=5.3.5; extra == "celery"
Requires-Dist: alyx_connector>=2.1.5; extra == "celery"
Provides-Extra: docs
Requires-Dist: mkdocs-material>=9.6.14; extra == "docs"
Requires-Dist: mkdocs-plugin-inline-svg>=0.1.0; extra == "docs"
